kernaux/__init__.py
kernaux/example.py
kernaux-0.0.0.dist-info/METADATA
kernaux-0.0.0.dist-info/WHEEL
kernaux-0.0.0.dist-info/top_level.txt
kernaux-0.0.0.dist-info/RECORD
