Metadata-Version: 2.1
Name: kernaux
Version: 0.0.0
Summary: Bindings to libkernaux - auxiliary library for kernel development
Home-page: https://github.com/tailix/libkernaux
Author: Alex Kotov
Author-email: kotovalexarian@gmail.com
License: UNKNOWN
Project-URL: Bug Tracker, https://github.com/tailix/libkernaux/issues
Platform: UNKNOWN
Classifier: Programming Language :: Python :: 3
Classifier: License :: OSI Approved :: MIT License
Classifier: Operating System :: POSIX
Requires-Python: >=3.8
